py2safe/__init__.py
py2safe/main.py
py2safe-2025.3.24.1.dist-info/LICENSE
py2safe-2025.3.24.1.dist-info/METADATA
py2safe-2025.3.24.1.dist-info/WHEEL
py2safe-2025.3.24.1.dist-info/entry_points.txt
py2safe-2025.3.24.1.dist-info/top_level.txt
py2safe-2025.3.24.1.dist-info/RECORD
