Metadata-Version: 2.1
Name: py2safe
Version: 2025.3.24.1
Summary: 为你的python项目一键加密
Author-email: YanChengxin <yan.cheng.xin@foxmail.com>
Project-URL: Homepage, https://gitee.com/yanchengxin2018/py2safe
Project-URL: Issues, https://gitee.com/yanchengxin2018/py2safe/issues
Classifier: Programming Language :: Python :: 3
Classifier: License :: OSI Approved :: MIT License
Classifier: Operating System :: OS Independent
Requires-Python: >=3.8.20
License-File: LICENSE
Requires-Dist: pyarmor ==9.1.1
